solarcalendar/__init__.py
SolarCalendar-0.1.1.dist-info/LICENCE
SolarCalendar-0.1.1.dist-info/METADATA
SolarCalendar-0.1.1.dist-info/WHEEL
SolarCalendar-0.1.1.dist-info/top_level.txt
SolarCalendar-0.1.1.dist-info/RECORD
