Metadata-Version: 2.1
Name: SolarCalendar
Version: 0.1.1
Summary: This module allows you to output calendars like the Unix jcal program,
Home-page: https://github.com/kamyarmg/solarcalendar
Author: Kamyar Ghanbarpour
Author-email: kmgirmia@gmail.com
License: UNKNOWN
Project-URL: Bug Tracker, https://github.com/kamyarmg/solarcalendar/issues
Platform: UNKNOWN
Classifier: Programming Language :: Python :: 3
Classifier: License :: OSI Approved :: MIT License
Classifier: Operating System :: OS Independent
Requires-Python: >=3.6
License-File: LICENCE
Requires-Dist: jdatetime (>=3.8.0)
